odoo/addons/l10n_th_tier_department/README.rst
odoo/addons/l10n_th_tier_department/__init__.py
odoo/addons/l10n_th_tier_department/__manifest__.py
odoo/addons/l10n_th_tier_department/i18n/l10n_th_tier_department.pot
odoo/addons/l10n_th_tier_department/models/__init__.py
odoo/addons/l10n_th_tier_department/models/hr_department.py
odoo/addons/l10n_th_tier_department/models/tier_level.py
odoo/addons/l10n_th_tier_department/readme/CONTRIBUTORS.md
odoo/addons/l10n_th_tier_department/readme/DESCRIPTION.md
odoo/addons/l10n_th_tier_department/readme/USAGE.md
odoo/addons/l10n_th_tier_department/security/ir.model.access.csv
odoo/addons/l10n_th_tier_department/security/tier_validation_department_security.xml
odoo/addons/l10n_th_tier_department/static/description/icon.png
odoo/addons/l10n_th_tier_department/static/description/index.html
odoo/addons/l10n_th_tier_department/templates/tier_validation_templates.xml
odoo/addons/l10n_th_tier_department/tests/__init__.py
odoo/addons/l10n_th_tier_department/tests/test_tier_validation_department.py
odoo/addons/l10n_th_tier_department/views/hr_department_views.xml
odoo/addons/l10n_th_tier_department/views/tier_level_views.xml
odoo_addon_l10n_th_tier_department-18.0.1.0.0.2.dist-info/METADATA
odoo_addon_l10n_th_tier_department-18.0.1.0.0.2.dist-info/WHEEL
odoo_addon_l10n_th_tier_department-18.0.1.0.0.2.dist-info/top_level.txt
odoo_addon_l10n_th_tier_department-18.0.1.0.0.2.dist-info/RECORD
